SourceWatch/__init__.py
SourceWatch/buffer.py
SourceWatch/models.py
SourceWatch/packet.py
SourceWatch/query.py
SourceWatch/server.py
sourcewatch-0.0.9.dist-info/METADATA
sourcewatch-0.0.9.dist-info/WHEEL
sourcewatch-0.0.9.dist-info/licenses/LICENSE
sourcewatch-0.0.9.dist-info/RECORD
