Metadata-Version: 2.4
Name: sourcewatch
Version: 0.0.9
Summary: A library to query information of Goldsrc and Source servers.
Project-URL: Homepage, https://github.com/SourceWatch/SourceWatch
Project-URL: Repository, https://github.com/SourceWatch/SourceWatch
Project-URL: Issues, https://github.com/SourceWatch/SourceWatch/issues
Author-email: Alex Kuhrt <alex@qrt.de>
License: The MIT License
License-File: LICENSE
Keywords: goldsrc,mcp,query,server,source,steam,valve
Classifier: Development Status :: 4 - Beta
Classifier: Intended Audience :: Developers
Classifier: License :: OSI Approved :: MIT License
Classifier: Operating System :: OS Independent
Classifier: Programming Language :: Python :: 3
Classifier: Programming Language :: Python :: 3.8
Classifier: Programming Language :: Python :: 3.9
Classifier: Programming Language :: Python :: 3.10
Classifier: Programming Language :: Python :: 3.11
Classifier: Programming Language :: Python :: 3.12
Classifier: Topic :: Games/Entertainment
Classifier: Topic :: Internet
Classifier: Topic :: Software Development :: Libraries :: Python Modules
Requires-Python: >=3.8
Requires-Dist: pydantic>=2.0.0
